{
  "teamId": 2132,
  "team": "Cincinnati",
  "normalizedName": "cincinnati",
  "schedule": [
    {
      "normalizedName": "cincinnati",
      "opponent": "Eastern Kentucky",
      "normalizedOpponent": "eastern-kentucky",
      "homeGame": true,
      "winLoss": "W",
      "id": 401525818,
      "season": 2023,
      "week": 1,
      "season_type": "regular",
      "start_date": "2023-09-02T19:30:00.000Z",
      "start_time_tbd": false,
      "completed": true,
      "neutral_site": false,
      "conference_game": false,
      "attendance": 38193,
      "venue_id": 3854,
      "venue": "Nippert Stadium",
      "home_id": 2132,
      "home_team": "Cincinnati",
      "home_conference": "Big 12",
      "home_division": "fbs",
      "home_points": 66,
      "home_line_scores": [
        21,
        21,
        10,
        14
      ],
      "home_post_win_prob": "0.9989357538894403",
      "home_pregame_elo": 1626,
      "home_postgame_elo": 1626,
      "away_id": 2198,
      "away_team": "Eastern Kentucky",
      "away_conference": "UAC",
      "away_division": "fcs",
      "away_points": 13,
      "away_line_scores": [
        0,
        7,
        3,
        3
      ],
      "away_post_win_prob": "0.0010642461105596634",
      "away_pregame_elo": null,
      "away_postgame_elo": null,
      "excitement_index": "2.3656523066",
      "highlights": null,
      "notes": null
    },
    {
      "normalizedName": "cincinnati",
      "opponent": "Pittsburgh",
      "normalizedOpponent": "pittsburgh",
      "homeGame": false,
      "winLoss": "W",
      "id": 401525496,
      "season": 2023,
      "week": 2,
      "season_type": "regular",
      "start_date": "2023-09-09T22:30:00.000Z",
      "start_time_tbd": false,
      "completed": true,
      "neutral_site": false,
      "conference_game": false,
      "attendance": 49398,
      "venue_id": 3752,
      "venue": "Heinz Field",
      "home_id": 221,
      "home_team": "Pittsburgh",
      "home_conference": "ACC",
      "home_division": "fbs",
      "home_points": 21,
      "home_line_scores": [
        7,
        0,
        0,
        14
      ],
      "home_post_win_prob": "0.00292031897467688",
      "home_pregame_elo": 1624,
      "home_postgame_elo": 1613,
      "away_id": 2132,
      "away_team": "Cincinnati",
      "away_conference": "Big 12",
      "away_division": "fbs",
      "away_points": 27,
      "away_line_scores": [
        10,
        10,
        7,
        0
      ],
      "away_post_win_prob": "0.9970796810253231",
      "away_pregame_elo": 1626,
      "away_postgame_elo": 1637,
      "excitement_index": "4.8088156659",
      "highlights": null,
      "notes": null
    },
    {
      "normalizedName": "cincinnati",
      "opponent": "Miami (OH)",
      "normalizedOpponent": "miami-oh",
      "homeGame": true,
      "winLoss": "L",
      "id": 401525835,
      "season": 2023,
      "week": 3,
      "season_type": "regular",
      "start_date": "2023-09-16T23:00:00.000Z",
      "start_time_tbd": false,
      "completed": true,
      "neutral_site": false,
      "conference_game": false,
      "attendance": 38193,
      "venue_id": 3854,
      "venue": "Nippert Stadium",
      "home_id": 2132,
      "home_team": "Cincinnati",
      "home_conference": "Big 12",
      "home_division": "fbs",
      "home_points": 24,
      "home_line_scores": [
        10,
        3,
        3,
        8,
        0
      ],
      "home_post_win_prob": "0.34909601627834885",
      "home_pregame_elo": 1637,
      "home_postgame_elo": 1597,
      "away_id": 193,
      "away_team": "Miami (OH)",
      "away_conference": "Mid-American",
      "away_division": "fbs",
      "away_points": 31,
      "away_line_scores": [
        7,
        7,
        7,
        3,
        7
      ],
      "away_post_win_prob": "0.6509039837216511",
      "away_pregame_elo": 1321,
      "away_postgame_elo": 1361,
      "excitement_index": "9.5476167808",
      "highlights": null,
      "notes": null
    },
    {
      "normalizedName": "cincinnati",
      "opponent": "Oklahoma",
      "normalizedOpponent": "oklahoma",
      "homeGame": true,
      "winLoss": "L",
      "id": 401525845,
      "season": 2023,
      "week": 4,
      "season_type": "regular",
      "start_date": "2023-09-23T16:00:00.000Z",
      "start_time_tbd": false,
      "completed": true,
      "neutral_site": false,
      "conference_game": true,
      "attendance": null,
      "venue_id": 3854,
      "venue": "Nippert Stadium",
      "home_id": 2132,
      "home_team": "Cincinnati",
      "home_conference": "Big 12",
      "home_division": "fbs",
      "home_points": 6,
      "home_line_scores": [
        3,
        0,
        3,
        0
      ],
      "home_post_win_prob": "0.008925422930566656",
      "home_pregame_elo": 1597,
      "home_postgame_elo": 1593,
      "away_id": 201,
      "away_team": "Oklahoma",
      "away_conference": "Big 12",
      "away_division": "fbs",
      "away_points": 20,
      "away_line_scores": [
        7,
        3,
        7,
        3
      ],
      "away_post_win_prob": "0.9910745770694334",
      "away_pregame_elo": 1897,
      "away_postgame_elo": 1901,
      "excitement_index": "4.9863960971",
      "highlights": null,
      "notes": null
    },
    {
      "normalizedName": "cincinnati",
      "opponent": "BYU",
      "normalizedOpponent": "byu",
      "homeGame": false,
      "winLoss": "L",
      "id": 401525851,
      "season": 2023,
      "week": 5,
      "season_type": "regular",
      "start_date": "2023-09-30T02:15:00.000Z",
      "start_time_tbd": false,
      "completed": true,
      "neutral_site": false,
      "conference_game": true,
      "attendance": null,
      "venue_id": 3801,
      "venue": "LaVell Edwards Stadium",
      "home_id": 252,
      "home_team": "BYU",
      "home_conference": "Big 12",
      "home_division": "fbs",
      "home_points": 35,
      "home_line_scores": [
        7,
        7,
        14,
        7
      ],
      "home_post_win_prob": "0.633421093924542",
      "home_pregame_elo": 1536,
      "home_postgame_elo": 1552,
      "away_id": 2132,
      "away_team": "Cincinnati",
      "away_conference": "Big 12",
      "away_division": "fbs",
      "away_points": 27,
      "away_line_scores": [
        0,
        10,
        10,
        7
      ],
      "away_post_win_prob": "0.36657890607545796",
      "away_pregame_elo": 1593,
      "away_postgame_elo": 1577,
      "excitement_index": "7.0034221565",
      "highlights": null,
      "notes": null
    },
    {
      "normalizedName": "cincinnati",
      "opponent": "Iowa State",
      "normalizedOpponent": "iowa-state",
      "homeGame": true,
      "winLoss": "L",
      "id": 401525863,
      "season": 2023,
      "week": 7,
      "season_type": "regular",
      "start_date": "2023-10-14T16:00:00.000Z",
      "start_time_tbd": false,
      "completed": true,
      "neutral_site": false,
      "conference_game": true,
      "attendance": null,
      "venue_id": 3854,
      "venue": "Nippert Stadium",
      "home_id": 2132,
      "home_team": "Cincinnati",
      "home_conference": "Big 12",
      "home_division": "fbs",
      "home_points": 10,
      "home_line_scores": [
        7,
        0,
        3,
        0
      ],
      "home_post_win_prob": "0.012301841509757442",
      "home_pregame_elo": 1577,
      "home_postgame_elo": 1522,
      "away_id": 66,
      "away_team": "Iowa State",
      "away_conference": "Big 12",
      "away_division": "fbs",
      "away_points": 30,
      "away_line_scores": [
        3,
        14,
        6,
        7
      ],
      "away_post_win_prob": "0.9876981584902426",
      "away_pregame_elo": 1540,
      "away_postgame_elo": 1595,
      "excitement_index": "3.4853145074",
      "highlights": null,
      "notes": null
    },
    {
      "normalizedName": "cincinnati",
      "opponent": "Baylor",
      "normalizedOpponent": "baylor",
      "homeGame": true,
      "winLoss": "L",
      "id": 401525868,
      "season": 2023,
      "week": 8,
      "season_type": "regular",
      "start_date": "2023-10-21T16:00:00.000Z",
      "start_time_tbd": false,
      "completed": true,
      "neutral_site": false,
      "conference_game": true,
      "attendance": null,
      "venue_id": 3854,
      "venue": "Nippert Stadium",
      "home_id": 2132,
      "home_team": "Cincinnati",
      "home_conference": "Big 12",
      "home_division": "fbs",
      "home_points": 29,
      "home_line_scores": [
        0,
        14,
        0,
        15
      ],
      "home_post_win_prob": "0.9143934850338465",
      "home_pregame_elo": 1522,
      "home_postgame_elo": 1514,
      "away_id": 239,
      "away_team": "Baylor",
      "away_conference": "Big 12",
      "away_division": "fbs",
      "away_points": 32,
      "away_line_scores": [
        3,
        17,
        9,
        3
      ],
      "away_post_win_prob": "0.08560651496615346",
      "away_pregame_elo": 1459,
      "away_postgame_elo": 1467,
      "excitement_index": "9.1878023596",
      "highlights": null,
      "notes": null
    },
    {
      "normalizedName": "cincinnati",
      "opponent": "Oklahoma State",
      "normalizedOpponent": "oklahoma-state",
      "homeGame": false,
      "winLoss": "L",
      "id": 401525876,
      "season": 2023,
      "week": 9,
      "season_type": "regular",
      "start_date": "2023-10-29T00:00:00.000Z",
      "start_time_tbd": false,
      "completed": true,
      "neutral_site": false,
      "conference_game": true,
      "attendance": null,
      "venue_id": 3646,
      "venue": "Boone Pickens Stadium",
      "home_id": 197,
      "home_team": "Oklahoma State",
      "home_conference": "Big 12",
      "home_division": "fbs",
      "home_points": 45,
      "home_line_scores": [
        7,
        3,
        21,
        14
      ],
      "home_post_win_prob": "0.9172079631525902",
      "home_pregame_elo": 1540,
      "home_postgame_elo": 1624,
      "away_id": 2132,
      "away_team": "Cincinnati",
      "away_conference": "Big 12",
      "away_division": "fbs",
      "away_points": 13,
      "away_line_scores": [
        7,
        0,
        0,
        6
      ],
      "away_post_win_prob": "0.08279203684740977",
      "away_pregame_elo": 1514,
      "away_postgame_elo": 1430,
      "excitement_index": "5.0313564455",
      "highlights": null,
      "notes": null
    },
    {
      "normalizedName": "cincinnati",
      "opponent": "UCF",
      "normalizedOpponent": "ucf",
      "homeGame": true,
      "winLoss": "L",
      "id": 401525881,
      "season": 2023,
      "week": 10,
      "season_type": "regular",
      "start_date": "2023-11-04T19:30:00.000Z",
      "start_time_tbd": false,
      "completed": true,
      "neutral_site": false,
      "conference_game": true,
      "attendance": null,
      "venue_id": 3854,
      "venue": "Nippert Stadium",
      "home_id": 2132,
      "home_team": "Cincinnati",
      "home_conference": "Big 12",
      "home_division": "fbs",
      "home_points": 26,
      "home_line_scores": [
        3,
        7,
        7,
        9
      ],
      "home_post_win_prob": "0.3383405041964251",
      "home_pregame_elo": 1430,
      "home_postgame_elo": 1431,
      "away_id": 2116,
      "away_team": "UCF",
      "away_conference": "Big 12",
      "away_division": "fbs",
      "away_points": 28,
      "away_line_scores": [
        7,
        7,
        7,
        7
      ],
      "away_post_win_prob": "0.6616594958035749",
      "away_pregame_elo": 1508,
      "away_postgame_elo": 1507,
      "excitement_index": "8.0847547351",
      "highlights": null,
      "notes": null
    },
    {
      "normalizedName": "cincinnati",
      "opponent": "Houston",
      "normalizedOpponent": "houston",
      "homeGame": false,
      "winLoss": "W",
      "id": 401525887,
      "season": 2023,
      "week": 11,
      "season_type": "regular",
      "start_date": "2023-11-12T00:00:00.000Z",
      "start_time_tbd": false,
      "completed": true,
      "neutral_site": false,
      "conference_game": true,
      "attendance": null,
      "venue_id": 4728,
      "venue": "John O'Quinn Field at TDECU Stadium",
      "home_id": 248,
      "home_team": "Houston",
      "home_conference": "Big 12",
      "home_division": "fbs",
      "home_points": 14,
      "home_line_scores": [
        0,
        7,
        0,
        7
      ],
      "home_post_win_prob": "0.08109892399012175",
      "home_pregame_elo": 1482,
      "home_postgame_elo": 1457,
      "away_id": 2132,
      "away_team": "Cincinnati",
      "away_conference": "Big 12",
      "away_division": "fbs",
      "away_points": 24,
      "away_line_scores": [
        7,
        7,
        3,
        7
      ],
      "away_post_win_prob": "0.9189010760098782",
      "away_pregame_elo": 1431,
      "away_postgame_elo": 1456,
      "excitement_index": "3.7663213726",
      "highlights": null,
      "notes": null
    },
    {
      "normalizedName": "cincinnati",
      "opponent": "West Virginia",
      "normalizedOpponent": "west-virginia",
      "homeGame": false,
      "winLoss": "L",
      "id": 401525899,
      "season": 2023,
      "week": 12,
      "season_type": "regular",
      "start_date": "2023-11-18T19:30:00.000Z",
      "start_time_tbd": false,
      "completed": true,
      "neutral_site": false,
      "conference_game": true,
      "attendance": null,
      "venue_id": 3842,
      "venue": "Mountaineer Field at Milan Puskar Stadium",
      "home_id": 277,
      "home_team": "West Virginia",
      "home_conference": "Big 12",
      "home_division": "fbs",
      "home_points": 42,
      "home_line_scores": [
        7,
        21,
        14,
        0
      ],
      "home_post_win_prob": "0.9988363307327495",
      "home_pregame_elo": 1508,
      "home_postgame_elo": 1552,
      "away_id": 2132,
      "away_team": "Cincinnati",
      "away_conference": "Big 12",
      "away_division": "fbs",
      "away_points": 21,
      "away_line_scores": [
        0,
        7,
        0,
        14
      ],
      "away_post_win_prob": "0.0011636692672505333",
      "away_pregame_elo": 1456,
      "away_postgame_elo": 1412,
      "excitement_index": "3.6059634769",
      "highlights": null,
      "notes": null
    },
    {
      "normalizedName": "cincinnati",
      "opponent": "Kansas",
      "normalizedOpponent": "kansas",
      "homeGame": true,
      "winLoss": "L",
      "id": 401525903,
      "season": 2023,
      "week": 13,
      "season_type": "regular",
      "start_date": "2023-11-26T00:30:00.000Z",
      "start_time_tbd": false,
      "completed": true,
      "neutral_site": false,
      "conference_game": true,
      "attendance": null,
      "venue_id": 3854,
      "venue": "Nippert Stadium",
      "home_id": 2132,
      "home_team": "Cincinnati",
      "home_conference": "Big 12",
      "home_division": "fbs",
      "home_points": 16,
      "home_line_scores": [
        3,
        7,
        0,
        6
      ],
      "home_post_win_prob": "0.004222081228481119",
      "home_pregame_elo": 1412,
      "home_postgame_elo": 1342,
      "away_id": 2305,
      "away_team": "Kansas",
      "away_conference": "Big 12",
      "away_division": "fbs",
      "away_points": 49,
      "away_line_scores": [
        0,
        21,
        7,
        21
      ],
      "away_post_win_prob": "0.9957779187715189",
      "away_pregame_elo": 1601,
      "away_postgame_elo": 1671,
      "excitement_index": "2.9836862265",
      "highlights": null,
      "notes": null
    }
  ]
}