{
  "teamId": 238,
  "team": "Vanderbilt",
  "normalizedName": "vanderbilt",
  "schedule": [
    {
      "normalizedName": "vanderbilt",
      "opponent": "Hawai'i",
      "normalizedOpponent": "hawaii",
      "homeGame": true,
      "winLoss": "W",
      "id": 401520147,
      "season": 2023,
      "week": 1,
      "season_type": "regular",
      "start_date": "2023-08-26T23:30:00.000Z",
      "start_time_tbd": false,
      "completed": true,
      "neutral_site": false,
      "conference_game": false,
      "attendance": 21407,
      "venue_id": 3973,
      "venue": "Vanderbilt Stadium",
      "home_id": 238,
      "home_team": "Vanderbilt",
      "home_conference": "SEC",
      "home_division": "fbs",
      "home_points": 35,
      "home_line_scores": [
        14,
        7,
        7,
        7
      ],
      "home_post_win_prob": "0.18084618805030608",
      "home_pregame_elo": 1322,
      "home_postgame_elo": 1327,
      "away_id": 62,
      "away_team": "Hawai'i",
      "away_conference": "Mountain West",
      "away_division": "fbs",
      "away_points": 28,
      "away_line_scores": [
        7,
        7,
        0,
        14
      ],
      "away_post_win_prob": "0.8191538119496939",
      "away_pregame_elo": 1246,
      "away_postgame_elo": 1241,
      "excitement_index": "5.2820326034",
      "highlights": null,
      "notes": null
    },
    {
      "normalizedName": "vanderbilt",
      "opponent": "Alabama A&M",
      "normalizedOpponent": "alabama-a-m",
      "homeGame": true,
      "winLoss": "W",
      "id": 401520178,
      "season": 2023,
      "week": 1,
      "season_type": "regular",
      "start_date": "2023-09-02T23:00:00.000Z",
      "start_time_tbd": false,
      "completed": true,
      "neutral_site": false,
      "conference_game": false,
      "attendance": 22035,
      "venue_id": 3973,
      "venue": "Vanderbilt Stadium",
      "home_id": 238,
      "home_team": "Vanderbilt",
      "home_conference": "SEC",
      "home_division": "fbs",
      "home_points": 47,
      "home_line_scores": [
        5,
        7,
        14,
        21
      ],
      "home_post_win_prob": "0.9185456621495672",
      "home_pregame_elo": 1238,
      "home_postgame_elo": 1238,
      "away_id": 2010,
      "away_team": "Alabama A&M",
      "away_conference": "SWAC",
      "away_division": "fcs",
      "away_points": 13,
      "away_line_scores": [
        3,
        0,
        7,
        3
      ],
      "away_post_win_prob": "0.08145433785043277",
      "away_pregame_elo": null,
      "away_postgame_elo": null,
      "excitement_index": "4.9678683510",
      "highlights": null,
      "notes": null
    },
    {
      "normalizedName": "vanderbilt",
      "opponent": "Wake Forest",
      "normalizedOpponent": "wake-forest",
      "homeGame": false,
      "winLoss": "L",
      "id": 401520216,
      "season": 2023,
      "week": 2,
      "season_type": "regular",
      "start_date": "2023-09-09T15:00:00.000Z",
      "start_time_tbd": false,
      "completed": true,
      "neutral_site": false,
      "conference_game": false,
      "attendance": 28363,
      "venue_id": 3630,
      "venue": "BB&T Field",
      "home_id": 154,
      "home_team": "Wake Forest",
      "home_conference": "ACC",
      "home_division": "fbs",
      "home_points": 36,
      "home_line_scores": [
        3,
        21,
        3,
        9
      ],
      "home_post_win_prob": "0.956853765264342",
      "home_pregame_elo": 1608,
      "home_postgame_elo": 1618,
      "away_id": 238,
      "away_team": "Vanderbilt",
      "away_conference": "SEC",
      "away_division": "fbs",
      "away_points": 20,
      "away_line_scores": [
        0,
        14,
        0,
        6
      ],
      "away_post_win_prob": "0.04314623473565804",
      "away_pregame_elo": 1327,
      "away_postgame_elo": 1317,
      "excitement_index": "4.7702379432",
      "highlights": null,
      "notes": null
    },
    {
      "normalizedName": "vanderbilt",
      "opponent": "UNLV",
      "normalizedOpponent": "unlv",
      "homeGame": false,
      "winLoss": "L",
      "id": 401520247,
      "season": 2023,
      "week": 3,
      "season_type": "regular",
      "start_date": "2023-09-16T23:00:00.000Z",
      "start_time_tbd": false,
      "completed": true,
      "neutral_site": false,
      "conference_game": false,
      "attendance": 22582,
      "venue_id": 6501,
      "venue": "Allegiant Stadium",
      "home_id": 2439,
      "home_team": "UNLV",
      "home_conference": "Mountain West",
      "home_division": "fbs",
      "home_points": 40,
      "home_line_scores": [
        0,
        20,
        10,
        10
      ],
      "home_post_win_prob": "0.8697552200837356",
      "home_pregame_elo": 1340,
      "home_postgame_elo": 1341,
      "away_id": 238,
      "away_team": "Vanderbilt",
      "away_conference": "SEC",
      "away_division": "fbs",
      "away_points": 37,
      "away_line_scores": [
        10,
        7,
        0,
        20
      ],
      "away_post_win_prob": "0.13024477991626437",
      "away_pregame_elo": 1317,
      "away_postgame_elo": 1316,
      "excitement_index": "10.4147234702",
      "highlights": null,
      "notes": null
    },
    {
      "normalizedName": "vanderbilt",
      "opponent": "Kentucky",
      "normalizedOpponent": "kentucky",
      "homeGame": true,
      "winLoss": "L",
      "id": 401520274,
      "season": 2023,
      "week": 4,
      "season_type": "regular",
      "start_date": "2023-09-23T16:00:00.000Z",
      "start_time_tbd": false,
      "completed": true,
      "neutral_site": false,
      "conference_game": true,
      "attendance": null,
      "venue_id": 3973,
      "venue": "Vanderbilt Stadium",
      "home_id": 238,
      "home_team": "Vanderbilt",
      "home_conference": "SEC",
      "home_division": "fbs",
      "home_points": 28,
      "home_line_scores": [
        0,
        10,
        3,
        15
      ],
      "home_post_win_prob": "0.0008870349207535293",
      "home_pregame_elo": 1316,
      "home_postgame_elo": 1310,
      "away_id": 96,
      "away_team": "Kentucky",
      "away_conference": "SEC",
      "away_division": "fbs",
      "away_points": 45,
      "away_line_scores": [
        21,
        3,
        7,
        14
      ],
      "away_post_win_prob": "0.9991129650792465",
      "away_pregame_elo": 1669,
      "away_postgame_elo": 1675,
      "excitement_index": "2.9247764031",
      "highlights": null,
      "notes": null
    },
    {
      "normalizedName": "vanderbilt",
      "opponent": "Missouri",
      "normalizedOpponent": "missouri",
      "homeGame": true,
      "winLoss": "L",
      "id": 401520293,
      "season": 2023,
      "week": 5,
      "season_type": "regular",
      "start_date": "2023-09-30T20:00:00.000Z",
      "start_time_tbd": false,
      "completed": true,
      "neutral_site": false,
      "conference_game": true,
      "attendance": null,
      "venue_id": 3973,
      "venue": "Vanderbilt Stadium",
      "home_id": 238,
      "home_team": "Vanderbilt",
      "home_conference": "SEC",
      "home_division": "fbs",
      "home_points": 21,
      "home_line_scores": [
        7,
        0,
        0,
        14
      ],
      "home_post_win_prob": "0.0036633765922275846",
      "home_pregame_elo": 1310,
      "home_postgame_elo": 1289,
      "away_id": 142,
      "away_team": "Missouri",
      "away_conference": "SEC",
      "away_division": "fbs",
      "away_points": 38,
      "away_line_scores": [
        3,
        14,
        7,
        14
      ],
      "away_post_win_prob": "0.9963366234077724",
      "away_pregame_elo": 1508,
      "away_postgame_elo": 1529,
      "excitement_index": "3.6671535968",
      "highlights": null,
      "notes": null
    },
    {
      "normalizedName": "vanderbilt",
      "opponent": "Florida",
      "normalizedOpponent": "florida",
      "homeGame": false,
      "winLoss": "L",
      "id": 401520299,
      "season": 2023,
      "week": 6,
      "season_type": "regular",
      "start_date": "2023-10-07T20:00:00.000Z",
      "start_time_tbd": false,
      "completed": true,
      "neutral_site": false,
      "conference_game": true,
      "attendance": null,
      "venue_id": 3634,
      "venue": "Ben Hill Griffin Stadium",
      "home_id": 57,
      "home_team": "Florida",
      "home_conference": "SEC",
      "home_division": "fbs",
      "home_points": 38,
      "home_line_scores": [
        7,
        14,
        7,
        10
      ],
      "home_post_win_prob": "0.9977310183420081",
      "home_pregame_elo": 1565,
      "home_postgame_elo": 1595,
      "away_id": 238,
      "away_team": "Vanderbilt",
      "away_conference": "SEC",
      "away_division": "fbs",
      "away_points": 14,
      "away_line_scores": [
        7,
        0,
        7,
        0
      ],
      "away_post_win_prob": "0.002268981657991942",
      "away_pregame_elo": 1289,
      "away_postgame_elo": 1259,
      "excitement_index": "4.3697434472",
      "highlights": null,
      "notes": null
    },
    {
      "normalizedName": "vanderbilt",
      "opponent": "Georgia",
      "normalizedOpponent": "georgia",
      "homeGame": true,
      "winLoss": "L",
      "id": 401520327,
      "season": 2023,
      "week": 7,
      "season_type": "regular",
      "start_date": "2023-10-14T16:00:00.000Z",
      "start_time_tbd": false,
      "completed": true,
      "neutral_site": false,
      "conference_game": true,
      "attendance": null,
      "venue_id": 3973,
      "venue": "Vanderbilt Stadium",
      "home_id": 238,
      "home_team": "Vanderbilt",
      "home_conference": "SEC",
      "home_division": "fbs",
      "home_points": 20,
      "home_line_scores": [
        7,
        0,
        0,
        13
      ],
      "home_post_win_prob": "0.016700726666349676",
      "home_pregame_elo": 1259,
      "home_postgame_elo": 1292,
      "away_id": 61,
      "away_team": "Georgia",
      "away_conference": "SEC",
      "away_division": "fbs",
      "away_points": 37,
      "away_line_scores": [
        7,
        17,
        3,
        10
      ],
      "away_post_win_prob": "0.9832992733336503",
      "away_pregame_elo": 2103,
      "away_postgame_elo": 2070,
      "excitement_index": "3.2212046423",
      "highlights": null,
      "notes": null
    },
    {
      "normalizedName": "vanderbilt",
      "opponent": "Ole Miss",
      "normalizedOpponent": "ole-miss",
      "homeGame": false,
      "winLoss": "L",
      "id": 401520357,
      "season": 2023,
      "week": 9,
      "season_type": "regular",
      "start_date": "2023-10-28T23:30:00.000Z",
      "start_time_tbd": false,
      "completed": true,
      "neutral_site": false,
      "conference_game": true,
      "attendance": null,
      "venue_id": 3974,
      "venue": "Vaught-Hemingway Stadium",
      "home_id": 145,
      "home_team": "Ole Miss",
      "home_conference": "SEC",
      "home_division": "fbs",
      "home_points": 33,
      "home_line_scores": [
        13,
        13,
        0,
        7
      ],
      "home_post_win_prob": "0.9980990890605073",
      "home_pregame_elo": 1689,
      "home_postgame_elo": 1713,
      "away_id": 238,
      "away_team": "Vanderbilt",
      "away_conference": "SEC",
      "away_division": "fbs",
      "away_points": 7,
      "away_line_scores": [
        0,
        0,
        7,
        0
      ],
      "away_post_win_prob": "0.0019009109394927393",
      "away_pregame_elo": 1292,
      "away_postgame_elo": 1268,
      "excitement_index": "3.0522687039",
      "highlights": null,
      "notes": null
    },
    {
      "normalizedName": "vanderbilt",
      "opponent": "Auburn",
      "normalizedOpponent": "auburn",
      "homeGame": true,
      "winLoss": "L",
      "id": 401520379,
      "season": 2023,
      "week": 10,
      "season_type": "regular",
      "start_date": "2023-11-04T20:00:00.000Z",
      "start_time_tbd": false,
      "completed": true,
      "neutral_site": false,
      "conference_game": true,
      "attendance": null,
      "venue_id": 3973,
      "venue": "Vanderbilt Stadium",
      "home_id": 238,
      "home_team": "Vanderbilt",
      "home_conference": "SEC",
      "home_division": "fbs",
      "home_points": 15,
      "home_line_scores": [
        0,
        7,
        8,
        0
      ],
      "home_post_win_prob": "0.029627546561604858",
      "home_pregame_elo": 1268,
      "home_postgame_elo": 1261,
      "away_id": 2,
      "away_team": "Auburn",
      "away_conference": "SEC",
      "away_division": "fbs",
      "away_points": 31,
      "away_line_scores": [
        14,
        3,
        14,
        0
      ],
      "away_post_win_prob": "0.9703724534383952",
      "away_pregame_elo": 1583,
      "away_postgame_elo": 1590,
      "excitement_index": "3.5966950063",
      "highlights": null,
      "notes": null
    },
    {
      "normalizedName": "vanderbilt",
      "opponent": "South Carolina",
      "normalizedOpponent": "south-carolina",
      "homeGame": false,
      "winLoss": "L",
      "id": 401520396,
      "season": 2023,
      "week": 11,
      "season_type": "regular",
      "start_date": "2023-11-11T17:00:00.000Z",
      "start_time_tbd": false,
      "completed": true,
      "neutral_site": false,
      "conference_game": true,
      "attendance": null,
      "venue_id": 3994,
      "venue": "Williams-Brice Stadium",
      "home_id": 2579,
      "home_team": "South Carolina",
      "home_conference": "SEC",
      "home_division": "fbs",
      "home_points": 47,
      "home_line_scores": [
        6,
        7,
        14,
        20
      ],
      "home_post_win_prob": "0.9989287912773187",
      "home_pregame_elo": 1511,
      "home_postgame_elo": 1597,
      "away_id": 238,
      "away_team": "Vanderbilt",
      "away_conference": "SEC",
      "away_division": "fbs",
      "away_points": 6,
      "away_line_scores": [
        0,
        0,
        0,
        6
      ],
      "away_post_win_prob": "0.0010712087226812939",
      "away_pregame_elo": 1261,
      "away_postgame_elo": 1175,
      "excitement_index": "5.5028609145",
      "highlights": null,
      "notes": null
    },
    {
      "normalizedName": "vanderbilt",
      "opponent": "Tennessee",
      "normalizedOpponent": "tennessee",
      "homeGame": false,
      "winLoss": "L",
      "id": 401520442,
      "season": 2023,
      "week": 13,
      "season_type": "regular",
      "start_date": "2023-11-25T20:30:00.000Z",
      "start_time_tbd": false,
      "completed": true,
      "neutral_site": false,
      "conference_game": true,
      "attendance": null,
      "venue_id": 3853,
      "venue": "Neyland Stadium",
      "home_id": 2633,
      "home_team": "Tennessee",
      "home_conference": "SEC",
      "home_division": "fbs",
      "home_points": 48,
      "home_line_scores": [
        14,
        17,
        14,
        3
      ],
      "home_post_win_prob": "0.993727541165205",
      "home_pregame_elo": 1787,
      "home_postgame_elo": 1786,
      "away_id": 238,
      "away_team": "Vanderbilt",
      "away_conference": "SEC",
      "away_division": "fbs",
      "away_points": 24,
      "away_line_scores": [
        7,
        3,
        0,
        14
      ],
      "away_post_win_prob": "0.006272458834794992",
      "away_pregame_elo": 1175,
      "away_postgame_elo": 1176,
      "excitement_index": "5.8917547354",
      "highlights": null,
      "notes": null
    }
  ]
}