{
  "teamId": 349,
  "team": "Army",
  "normalizedName": "army",
  "schedule": [
    {
      "normalizedName": "army",
      "opponent": "Louisiana Monroe",
      "normalizedOpponent": "louisiana-monroe",
      "homeGame": false,
      "winLoss": "",
      "id": 401520175,
      "season": 2023,
      "week": 1,
      "season_type": "regular",
      "start_date": "2023-09-02T23:00:00.000Z",
      "start_time_tbd": false,
      "completed": false,
      "neutral_site": false,
      "conference_game": false,
      "attendance": null,
      "venue_id": 3817,
      "venue": "Malone Stadium",
      "home_id": 2433,
      "home_team": "Louisiana Monroe",
      "home_conference": "Sun Belt",
      "home_division": "fbs",
      "home_points": null,
      "home_line_scores": null,
      "home_post_win_prob": null,
      "home_pregame_elo": 1207,
      "home_postgame_elo": null,
      "away_id": 349,
      "away_team": "Army",
      "away_conference": "FBS Independents",
      "away_division": "fbs",
      "away_points": null,
      "away_line_scores": null,
      "away_post_win_prob": null,
      "away_pregame_elo": 1544,
      "away_postgame_elo": null,
      "excitement_index": null,
      "highlights": null,
      "notes": null
    },
    {
      "normalizedName": "army",
      "opponent": "Delaware State",
      "normalizedOpponent": "delaware-state",
      "homeGame": true,
      "winLoss": "",
      "id": 401520185,
      "season": 2023,
      "week": 2,
      "season_type": "regular",
      "start_date": "2023-09-09T16:00:00.000Z",
      "start_time_tbd": false,
      "completed": false,
      "neutral_site": false,
      "conference_game": false,
      "attendance": null,
      "venue_id": 3841,
      "venue": "Blaik Field at Michie Stadium",
      "home_id": 349,
      "home_team": "Army",
      "home_conference": "FBS Independents",
      "home_division": "fbs",
      "home_points": null,
      "home_line_scores": null,
      "home_post_win_prob": null,
      "home_pregame_elo": null,
      "home_postgame_elo": null,
      "away_id": 2169,
      "away_team": "Delaware State",
      "away_conference": "MEAC",
      "away_division": "fcs",
      "away_points": null,
      "away_line_scores": null,
      "away_post_win_prob": null,
      "away_pregame_elo": null,
      "away_postgame_elo": null,
      "excitement_index": null,
      "highlights": null,
      "notes": null
    },
    {
      "normalizedName": "army",
      "opponent": "UT San Antonio",
      "normalizedOpponent": "ut-san-antonio",
      "homeGame": false,
      "winLoss": "",
      "id": 401531396,
      "season": 2023,
      "week": 3,
      "season_type": "regular",
      "start_date": "2023-09-15T23:00:00.000Z",
      "start_time_tbd": false,
      "completed": false,
      "neutral_site": false,
      "conference_game": false,
      "attendance": null,
      "venue_id": 3604,
      "venue": "Alamodome",
      "home_id": 2636,
      "home_team": "UT San Antonio",
      "home_conference": "American Athletic",
      "home_division": "fbs",
      "home_points": null,
      "home_line_scores": null,
      "home_post_win_prob": null,
      "home_pregame_elo": 1512,
      "home_postgame_elo": null,
      "away_id": 349,
      "away_team": "Army",
      "away_conference": "FBS Independents",
      "away_division": "fbs",
      "away_points": null,
      "away_line_scores": null,
      "away_post_win_prob": null,
      "away_pregame_elo": 1544,
      "away_postgame_elo": null,
      "excitement_index": null,
      "highlights": null,
      "notes": null
    },
    {
      "normalizedName": "army",
      "opponent": "Syracuse",
      "normalizedOpponent": "syracuse",
      "homeGame": false,
      "winLoss": "",
      "id": 401520268,
      "season": 2023,
      "week": 4,
      "season_type": "regular",
      "start_date": "2023-09-23T04:00:00.000Z",
      "start_time_tbd": true,
      "completed": false,
      "neutral_site": false,
      "conference_game": false,
      "attendance": null,
      "venue_id": 1964,
      "venue": "Carrier Dome",
      "home_id": 183,
      "home_team": "Syracuse",
      "home_conference": "ACC",
      "home_division": "fbs",
      "home_points": null,
      "home_line_scores": null,
      "home_post_win_prob": null,
      "home_pregame_elo": 1405,
      "home_postgame_elo": null,
      "away_id": 349,
      "away_team": "Army",
      "away_conference": "FBS Independents",
      "away_division": "fbs",
      "away_points": null,
      "away_line_scores": null,
      "away_post_win_prob": null,
      "away_pregame_elo": 1544,
      "away_postgame_elo": null,
      "excitement_index": null,
      "highlights": null,
      "notes": null
    },
    {
      "normalizedName": "army",
      "opponent": "Boston College",
      "normalizedOpponent": "boston-college",
      "homeGame": true,
      "winLoss": "",
      "id": 401520298,
      "season": 2023,
      "week": 6,
      "season_type": "regular",
      "start_date": "2023-10-07T16:00:00.000Z",
      "start_time_tbd": false,
      "completed": false,
      "neutral_site": false,
      "conference_game": false,
      "attendance": null,
      "venue_id": 3841,
      "venue": "Blaik Field at Michie Stadium",
      "home_id": 349,
      "home_team": "Army",
      "home_conference": "FBS Independents",
      "home_division": "fbs",
      "home_points": null,
      "home_line_scores": null,
      "home_post_win_prob": null,
      "home_pregame_elo": 1544,
      "home_postgame_elo": null,
      "away_id": 103,
      "away_team": "Boston College",
      "away_conference": "ACC",
      "away_division": "fbs",
      "away_points": null,
      "away_line_scores": null,
      "away_post_win_prob": null,
      "away_pregame_elo": 1443,
      "away_postgame_elo": null,
      "excitement_index": null,
      "highlights": null,
      "notes": null
    },
    {
      "normalizedName": "army",
      "opponent": "Troy",
      "normalizedOpponent": "troy",
      "homeGame": true,
      "winLoss": "",
      "id": 401520317,
      "season": 2023,
      "week": 7,
      "season_type": "regular",
      "start_date": "2023-10-14T19:30:00.000Z",
      "start_time_tbd": false,
      "completed": false,
      "neutral_site": false,
      "conference_game": false,
      "attendance": null,
      "venue_id": 3841,
      "venue": "Blaik Field at Michie Stadium",
      "home_id": 349,
      "home_team": "Army",
      "home_conference": "FBS Independents",
      "home_division": "fbs",
      "home_points": null,
      "home_line_scores": null,
      "home_post_win_prob": null,
      "home_pregame_elo": 1544,
      "home_postgame_elo": null,
      "away_id": 2653,
      "away_team": "Troy",
      "away_conference": "Sun Belt",
      "away_division": "fbs",
      "away_points": null,
      "away_line_scores": null,
      "away_post_win_prob": null,
      "away_pregame_elo": 1347,
      "away_postgame_elo": null,
      "excitement_index": null,
      "highlights": null,
      "notes": null
    },
    {
      "normalizedName": "army",
      "opponent": "LSU",
      "normalizedOpponent": "lsu",
      "homeGame": false,
      "winLoss": "",
      "id": 401520339,
      "season": 2023,
      "week": 8,
      "season_type": "regular",
      "start_date": "2023-10-21T04:00:00.000Z",
      "start_time_tbd": true,
      "completed": false,
      "neutral_site": false,
      "conference_game": false,
      "attendance": null,
      "venue_id": 3958,
      "venue": "Tiger Stadium",
      "home_id": 99,
      "home_team": "LSU",
      "home_conference": "SEC",
      "home_division": "fbs",
      "home_points": null,
      "home_line_scores": null,
      "home_post_win_prob": null,
      "home_pregame_elo": 1538,
      "home_postgame_elo": null,
      "away_id": 349,
      "away_team": "Army",
      "away_conference": "FBS Independents",
      "away_division": "fbs",
      "away_points": null,
      "away_line_scores": null,
      "away_post_win_prob": null,
      "away_pregame_elo": 1544,
      "away_postgame_elo": null,
      "excitement_index": null,
      "highlights": null,
      "notes": null
    },
    {
      "normalizedName": "army",
      "opponent": "UMass",
      "normalizedOpponent": "umass",
      "homeGame": true,
      "winLoss": "",
      "id": 401520349,
      "season": 2023,
      "week": 9,
      "season_type": "regular",
      "start_date": "2023-10-28T16:00:00.000Z",
      "start_time_tbd": false,
      "completed": false,
      "neutral_site": false,
      "conference_game": true,
      "attendance": null,
      "venue_id": 3841,
      "venue": "Blaik Field at Michie Stadium",
      "home_id": 349,
      "home_team": "Army",
      "home_conference": "FBS Independents",
      "home_division": "fbs",
      "home_points": null,
      "home_line_scores": null,
      "home_post_win_prob": null,
      "home_pregame_elo": 1544,
      "home_postgame_elo": null,
      "away_id": 113,
      "away_team": "UMass",
      "away_conference": "FBS Independents",
      "away_division": "fbs",
      "away_points": null,
      "away_line_scores": null,
      "away_post_win_prob": null,
      "away_pregame_elo": 1036,
      "away_postgame_elo": null,
      "excitement_index": null,
      "highlights": null,
      "notes": null
    },
    {
      "normalizedName": "army",
      "opponent": "Air Force",
      "normalizedOpponent": "air-force",
      "homeGame": false,
      "winLoss": "",
      "id": 401520361,
      "season": 2023,
      "week": 10,
      "season_type": "regular",
      "start_date": "2023-11-04T18:30:00.000Z",
      "start_time_tbd": false,
      "completed": false,
      "neutral_site": true,
      "conference_game": false,
      "attendance": null,
      "venue_id": 3937,
      "venue": "Sports Authority Field at Mile High",
      "home_id": 2005,
      "home_team": "Air Force",
      "home_conference": "Mountain West",
      "home_division": "fbs",
      "home_points": null,
      "home_line_scores": null,
      "home_post_win_prob": null,
      "home_pregame_elo": 1650,
      "home_postgame_elo": null,
      "away_id": 349,
      "away_team": "Army",
      "away_conference": "FBS Independents",
      "away_division": "fbs",
      "away_points": null,
      "away_line_scores": null,
      "away_post_win_prob": null,
      "away_pregame_elo": 1544,
      "away_postgame_elo": null,
      "excitement_index": null,
      "highlights": null,
      "notes": null
    },
    {
      "normalizedName": "army",
      "opponent": "Holy Cross",
      "normalizedOpponent": "holy-cross",
      "homeGame": true,
      "winLoss": "",
      "id": 401520381,
      "season": 2023,
      "week": 11,
      "season_type": "regular",
      "start_date": "2023-11-11T17:00:00.000Z",
      "start_time_tbd": false,
      "completed": false,
      "neutral_site": false,
      "conference_game": false,
      "attendance": null,
      "venue_id": 3841,
      "venue": "Blaik Field at Michie Stadium",
      "home_id": 349,
      "home_team": "Army",
      "home_conference": "FBS Independents",
      "home_division": "fbs",
      "home_points": null,
      "home_line_scores": null,
      "home_post_win_prob": null,
      "home_pregame_elo": null,
      "home_postgame_elo": null,
      "away_id": 107,
      "away_team": "Holy Cross",
      "away_conference": "Patriot",
      "away_division": "fcs",
      "away_points": null,
      "away_line_scores": null,
      "away_post_win_prob": null,
      "away_pregame_elo": null,
      "away_postgame_elo": null,
      "excitement_index": null,
      "highlights": null,
      "notes": null
    },
    {
      "normalizedName": "army",
      "opponent": "Coastal Carolina",
      "normalizedOpponent": "coastal-carolina",
      "homeGame": true,
      "winLoss": "",
      "id": 401520403,
      "season": 2023,
      "week": 12,
      "season_type": "regular",
      "start_date": "2023-11-18T17:00:00.000Z",
      "start_time_tbd": false,
      "completed": false,
      "neutral_site": false,
      "conference_game": false,
      "attendance": null,
      "venue_id": 3841,
      "venue": "Blaik Field at Michie Stadium",
      "home_id": 349,
      "home_team": "Army",
      "home_conference": "FBS Independents",
      "home_division": "fbs",
      "home_points": null,
      "home_line_scores": null,
      "home_post_win_prob": null,
      "home_pregame_elo": 1544,
      "home_postgame_elo": null,
      "away_id": 324,
      "away_team": "Coastal Carolina",
      "away_conference": "Sun Belt",
      "away_division": "fbs",
      "away_points": null,
      "away_line_scores": null,
      "away_post_win_prob": null,
      "away_pregame_elo": 1647,
      "away_postgame_elo": null,
      "excitement_index": null,
      "highlights": null,
      "notes": null
    },
    {
      "normalizedName": "army",
      "opponent": "Navy",
      "normalizedOpponent": "navy",
      "homeGame": true,
      "winLoss": "",
      "id": 401520445,
      "season": 2023,
      "week": 15,
      "season_type": "regular",
      "start_date": "2023-12-09T20:00:00.000Z",
      "start_time_tbd": false,
      "completed": false,
      "neutral_site": true,
      "conference_game": false,
      "attendance": null,
      "venue_id": 3738,
      "venue": "Gillette Stadium",
      "home_id": 349,
      "home_team": "Army",
      "home_conference": "FBS Independents",
      "home_division": "fbs",
      "home_points": null,
      "home_line_scores": null,
      "home_post_win_prob": null,
      "home_pregame_elo": 1544,
      "home_postgame_elo": null,
      "away_id": 2426,
      "away_team": "Navy",
      "away_conference": "American Athletic",
      "away_division": "fbs",
      "away_points": null,
      "away_line_scores": null,
      "away_post_win_prob": null,
      "away_pregame_elo": 1403,
      "away_postgame_elo": null,
      "excitement_index": null,
      "highlights": null,
      "notes": null
    }
  ]
}